{
  "groups": [
    {
      "name": "alipay",
      "type": "com.imooc3.resource.AliPayResource",
      "sourceType": "com.imooc3.resource.AliPayResource"
    },
    {
      "name": "wxpay",
      "type": "com.imooc3.resource.WXPayResource",
      "sourceType": "com.imooc3.resource.WXPayResource"
    }
  ],
  "properties": [
    {
      "name": "alipay.alipay-public-key",
      "type": "java.lang.String",
      "sourceType": "com.imooc3.resource.AliPayResource"
    },
    {
      "name": "alipay.app-id",
      "type": "java.lang.String",
      "sourceType": "com.imooc3.resource.AliPayResource"
    },
    {
      "name": "alipay.charset",
      "type": "java.lang.String",
      "sourceType": "com.imooc3.resource.AliPayResource"
    },
    {
      "name": "alipay.gateway-url",
      "type": "java.lang.String",
      "sourceType": "com.imooc3.resource.AliPayResource"
    },
    {
      "name": "alipay.merchant-private-key",
      "type": "java.lang.String",
      "sourceType": "com.imooc3.resource.AliPayResource"
    },
    {
      "name": "alipay.notify-url",
      "type": "java.lang.String",
      "sourceType": "com.imooc3.resource.AliPayResource"
    },
    {
      "name": "alipay.return-url",
      "type": "java.lang.String",
      "sourceType": "com.imooc3.resource.AliPayResource"
    },
    {
      "name": "alipay.sign-type",
      "type": "java.lang.String",
      "sourceType": "com.imooc3.resource.AliPayResource"
    },
    {
      "name": "wxpay.app-id",
      "type": "java.lang.String",
      "sourceType": "com.imooc3.resource.WXPayResource"
    },
    {
      "name": "wxpay.merchant-id",
      "type": "java.lang.String",
      "sourceType": "com.imooc3.resource.WXPayResource"
    },
    {
      "name": "wxpay.notify-url",
      "type": "java.lang.String",
      "sourceType": "com.imooc3.resource.WXPayResource"
    },
    {
      "name": "wxpay.place-order-url",
      "type": "java.lang.String",
      "sourceType": "com.imooc3.resource.WXPayResource"
    },
    {
      "name": "wxpay.qrcode-expire",
      "type": "java.lang.Long",
      "sourceType": "com.imooc3.resource.WXPayResource",
      "defaultValue": 0
    },
    {
      "name": "wxpay.qrcode-key",
      "type": "java.lang.String",
      "sourceType": "com.imooc3.resource.WXPayResource"
    },
    {
      "name": "wxpay.secrect-key",
      "type": "java.lang.String",
      "sourceType": "com.imooc3.resource.WXPayResource"
    },
    {
      "name": "wxpay.spbill-create-ip",
      "type": "java.lang.String",
      "sourceType": "com.imooc3.resource.WXPayResource"
    },
    {
      "name": "wxpay.trade-type",
      "type": "java.lang.String",
      "sourceType": "com.imooc3.resource.WXPayResource"
    }
  ],
  "hints": []
}